hypershell/__init__.py
hypershell/client.py
hypershell/cluster/__init__.py
hypershell/cluster/local.py
hypershell/cluster/remote.py
hypershell/cluster/ssh.py
hypershell/config.py
hypershell/core/__init__.py
hypershell/core/config.py
hypershell/core/exceptions.py
hypershell/core/fsm.py
hypershell/core/heartbeat.py
hypershell/core/logging.py
hypershell/core/platform.py
hypershell/core/queue.py
hypershell/core/remote.py
hypershell/core/signal.py
hypershell/core/template.py
hypershell/core/thread.py
hypershell/core/types.py
hypershell/data/__init__.py
hypershell/data/core.py
hypershell/data/model.py
hypershell/server.py
hypershell/submit.py
hypershell/task.py
hyper_shell-2.5.1.dist-info/LICENSE
hyper_shell-2.5.1.dist-info/METADATA
hyper_shell-2.5.1.dist-info/WHEEL
hyper_shell-2.5.1.dist-info/entry_points.txt
hyper_shell-2.5.1.dist-info/RECORD
