Metadata-Version: 2.1
Name: hyper-shell
Version: 2.5.1
Summary: A cross-platform, high-throughput computing utility for processing shell commands over a distributed, asynchronous queue.
Home-page: https://hyper-shell.readthedocs.io
License: Apache-2.0
Keywords: distributed-computing,command-line-tool,shell-scripting,high-performance-computing,high-throughput-computing
Author: Geoffrey Lentner
Author-email: glentner@purdue.edu
Requires-Python: >=3.10,<4.0
Classifier: Development Status :: 5 - Production/Stable
Classifier: License :: OSI Approved :: Apache Software License
Classifier: Operating System :: MacOS
Classifier: Operating System :: Microsoft :: Windows
Classifier: Operating System :: POSIX :: Linux
Classifier: Programming Language :: Python :: 3
Classifier: Programming Language :: Python :: 3.10
Classifier: Programming Language :: Python :: 3.11
Classifier: Programming Language :: Python :: 3.12
Classifier: Topic :: Utilities
Requires-Dist: cmdkit (>=2.7.5,<3.0.0)
Requires-Dist: paramiko (>=3.4.0,<4.0.0)
Requires-Dist: psycopg2 (>=2.9.9,<3.0.0)
Requires-Dist: rich (>=13.7.1,<14.0.0)
Requires-Dist: sqlalchemy (>=2.0.29,<3.0.0)
Requires-Dist: toml (>=0.10.2,<0.11.0)
Requires-Dist: tomlkit (>=0.12.4,<0.13.0)
Project-URL: Documentation, https://hyper-shell.readthedocs.io
Project-URL: Repository, https://github.com/glentner/hyper-shell
